doc2md2.py
doc2md2-0.1.3.dist-info/DESCRIPTION.rst
doc2md2-0.1.3.dist-info/METADATA
doc2md2-0.1.3.dist-info/RECORD
doc2md2-0.1.3.dist-info/WHEEL
doc2md2-0.1.3.dist-info/entry_points.txt
doc2md2-0.1.3.dist-info/metadata.json
doc2md2-0.1.3.dist-info/top_level.txt
