Metadata-Version: 2.0
Name: doc2md2
Version: 0.1.3
Summary: doc to markdown 
Home-page: https://github.com/kennethreitz/background
Author: yobrave
Author-email: yobrave86550129@yahoo.com
License: ISC
Platform: UNKNOWN
Classifier: Programming Language :: Python
Classifier: Programming Language :: Python :: 2.6
Classifier: Programming Language :: Python :: 2.7
Classifier: Programming Language :: Python :: 3
Classifier: Programming Language :: Python :: 3.3
Classifier: Programming Language :: Python :: 3.4
Classifier: Programming Language :: Python :: 3.5
Classifier: Programming Language :: Python :: 3.6
Classifier: Programming Language :: Python :: Implementation :: CPython
Classifier: Programming Language :: Python :: Implementation :: PyPy
Requires-Dist: termcolor
